scratchip/__init__.py
scratchip/main.py
scratchip/version.py
scratchip/assets/Demo.scala
scratchip/assets/build.sc
scratchip/assets/chisel.mk
scratchip/assets/default.yaml
scratchip/assets/gitignore
scratchip/assets/project.mk
scratchip/assets/project.yml
scratchip-0.3.1.dist-info/LICENSE
scratchip-0.3.1.dist-info/METADATA
scratchip-0.3.1.dist-info/WHEEL
scratchip-0.3.1.dist-info/entry_points.txt
scratchip-0.3.1.dist-info/top_level.txt
scratchip-0.3.1.dist-info/RECORD
